__init__.py
CV/__init__.py
CV/dataol.py
CV/infer_tool.py
CV/kmeans_anchor/__init__.py
CV/kmeans_anchor/optimize_anchor.py
CV/kmeans_anchor/read_voc.py
CV/kmeans_anchor/yolo_kmeans.py
CV/sample_test/__init__.py
CV/sample_test/test.py
cvenable-0.0.3.dist-info/LICENSE
cvenable-0.0.3.dist-info/METADATA
cvenable-0.0.3.dist-info/WHEEL
cvenable-0.0.3.dist-info/top_level.txt
cvenable-0.0.3.dist-info/RECORD
