Metadata-Version: 2.1
Name: cvenable
Version: 0.0.3
Summary: A small pakage for CV
Author-email: linweicheng <linweicheng5@huawei-partners.com>
Classifier: Programming Language :: Python :: 3
Classifier: License :: OSI Approved :: MIT License
Classifier: Operating System :: OS Independent
Requires-Python: >=3.7
License-File: LICENSE
